docker/_version.py
docker_custom_unofficial-1.0.1.dist-info/METADATA
docker_custom_unofficial-1.0.1.dist-info/WHEEL
docker_custom_unofficial-1.0.1.dist-info/licenses/LICENSE
docker_custom_unofficial-1.0.1.dist-info/RECORD
