Metadata-Version: 2.4
Name: docker_custom_unofficial
Version: 1.0.1
Summary: A Python library for the Docker Engine API. (with a modification to make ssh work again... as no clear configuration path for SSH was added for the new 'security' patches)
Project-URL: Changelog, https://docker-py.readthedocs.io/en/stable/change-log.html
Project-URL: Documentation, https://docker-py.readthedocs.io
Project-URL: Homepage, https://github.com/docker/docker-py
Project-URL: Source, https://github.com/docker/docker-py
Project-URL: Tracker, https://github.com/docker/docker-py/issues
Maintainer-email: Gordon MacPherson <gordon@gordonite.tech>
License-Expression: Apache-2.0
License-File: LICENSE
Classifier: Development Status :: 5 - Production/Stable
Classifier: Environment :: Other Environment
Classifier: Intended Audience :: Developers
Classifier: License :: OSI Approved :: Apache Software License
Classifier: Operating System :: OS Independent
Classifier: Programming Language :: Python
Classifier: Programming Language :: Python :: 3
Classifier: Programming Language :: Python :: 3.8
Classifier: Programming Language :: Python :: 3.9
Classifier: Programming Language :: Python :: 3.10
Classifier: Programming Language :: Python :: 3.11
Classifier: Programming Language :: Python :: 3.12
Classifier: Topic :: Software Development
Classifier: Topic :: Utilities
Requires-Python: >=3.8
Requires-Dist: pywin32>=304; sys_platform == 'win32'
Requires-Dist: requests>=2.26.0
Requires-Dist: urllib3>=1.26.0
Provides-Extra: dev
Requires-Dist: coverage==7.2.7; extra == 'dev'
Requires-Dist: pytest-cov==4.1.0; extra == 'dev'
Requires-Dist: pytest-timeout==2.1.0; extra == 'dev'
Requires-Dist: pytest==7.4.2; extra == 'dev'
Requires-Dist: ruff==0.1.8; extra == 'dev'
Provides-Extra: docs
Requires-Dist: myst-parser==0.18.0; extra == 'docs'
Requires-Dist: sphinx==5.1.1; extra == 'docs'
Provides-Extra: ssh
Requires-Dist: paramiko>=2.4.3; extra == 'ssh'
Provides-Extra: tls
Provides-Extra: websockets
Requires-Dist: websocket-client>=1.3.0; extra == 'websockets'
